yamlalchemy/__init__.py
yamlalchemy/constants.py
yamlalchemy/parser.py
yamlalchemy/statement.py
yamlalchemy-0.2.0.dist-info/licenses/LICENSE.txt
yamlalchemy-0.2.0.dist-info/METADATA
yamlalchemy-0.2.0.dist-info/WHEEL
yamlalchemy-0.2.0.dist-info/top_level.txt
yamlalchemy-0.2.0.dist-info/RECORD
