Metadata-Version: 2.4
Name: yamlalchemy
Version: 0.2.0
Summary: YAMLAlchemy is a Python-based library to convert YAML to SQLAlchemy read-only queries.
Home-page: https://github.com/ahmetonol/yamlalchemy
Author: Ahmet Onol
Author-email: onol.ahmet@gmail.com
License: MIT
Classifier: License :: OSI Approved :: MIT License
Classifier: Programming Language :: Python :: 3
Classifier: Programming Language :: Python :: 3.8
Classifier: Programming Language :: Python :: 3.9
Classifier: Programming Language :: Python :: 3.10
Classifier: Programming Language :: Python :: 3.11
Classifier: Programming Language :: Python :: 3.12
Requires-Python: >=3.8
License-File: LICENSE.txt
Requires-Dist: PyYAML
Requires-Dist: SQLAlchemy
Dynamic: author
Dynamic: author-email
Dynamic: classifier
Dynamic: description
Dynamic: description-content-type
Dynamic: home-page
Dynamic: license
Dynamic: license-file
Dynamic: requires-dist
Dynamic: requires-python
Dynamic: summary
